document_cropper/__init__.py
document_cropper/corner_detection.py
document_cropper/cropper_pipeline.py
document_cropper/image_cropper.py
document_cropper/segmentation.py
document_cropper-0.0.1.dist-info/LICENSE
document_cropper-0.0.1.dist-info/METADATA
document_cropper-0.0.1.dist-info/WHEEL
document_cropper-0.0.1.dist-info/top_level.txt
document_cropper-0.0.1.dist-info/RECORD
