Metadata-Version: 2.1
Name: document-cropper
Version: 0.0.1
Summary: For cropping documents from images
Home-page: https://github.com/KKroliKK/document-cropper
Author: Andrey Vagin
Author-email: kkrolikk759@gmail.com
Classifier: Programming Language :: Python :: 3
Classifier: License :: OSI Approved :: MIT License
Classifier: Operating System :: OS Independent
Requires-Python: >=3.8
License-File: LICENSE
Requires-Dist: numpy
Requires-Dist: matplotlib
Requires-Dist: scikit-image
